http_error_schemas/__init__.py
http_error_schemas/factory.py
http_error_schemas/schemas.py
http_error_schemas-1.0.1.dist-info/METADATA
http_error_schemas-1.0.1.dist-info/WHEEL
http_error_schemas-1.0.1.dist-info/top_level.txt
http_error_schemas-1.0.1.dist-info/RECORD
