Metadata-Version: 2.1
Name: http_error_schemas
Version: 1.0.1
Summary: HTTP Error Schemas
Home-page: https://github.com/TeiaLabs/http-error-schemas
Author: TeiaLabs
Author-email: contato@teialabs.com
Requires-Python: >=3.10
Requires-Dist: pydantic
